stm8dce/__init__.py
stm8dce/__main__.py
stm8dce/asm_analysis.py
stm8dce/asm_matchers.py
stm8dce/asm_parser.py
stm8dce/debug.py
stm8dce/rel_analysis.py
stm8dce/rel_matchers.py
stm8dce/rel_parser.py
stm8dce/settings.py
stm8dce-1.1.2.dist-info/METADATA
stm8dce-1.1.2.dist-info/WHEEL
stm8dce-1.1.2.dist-info/entry_points.txt
stm8dce-1.1.2.dist-info/licenses/LICENSE
stm8dce-1.1.2.dist-info/RECORD
