Metadata-Version: 2.3
Name: stm8dce
Version: 1.1.2
Summary: SDCC STM8 Dead Code Elimination Tool
Project-URL: Homepage, https://github.com/CTXz/STM8-DCE
Project-URL: Issues, https://github.com/CTXz/STM8-DCE/issues
Author-email: Patrick Pedersen <ctx.xda@gmail.com>
License-File: LICENSE
Classifier: License :: OSI Approved :: MIT License
Classifier: Operating System :: OS Independent
Classifier: Programming Language :: Python :: 3
Requires-Python: >=3.8
